hky3535/__init__.py
hky3535/api.py
hky3535/auto_label.py
hky3535/b64.py
hky3535/draw.py
hky3535/edit.py
hky3535/filter.py
hky3535/generate.py
hky3535/measure.py
hky3535/tracker.py
hky3535-0.1.7.dist-info/LICENSE
hky3535-0.1.7.dist-info/METADATA
hky3535-0.1.7.dist-info/WHEEL
hky3535-0.1.7.dist-info/top_level.txt
hky3535-0.1.7.dist-info/RECORD
