Metadata-Version: 2.1
Name: hky3535
Version: 0.1.7
Home-page: https://github.com/hky3535/hky3535.git
Author: hky3535
Author-email: hky3535@163.com
License: Apache
Classifier: License :: OSI Approved :: Apache Software License
License-File: LICENSE
Requires-Dist: opencv-python
Requires-Dist: numpy
Requires-Dist: pillow
Requires-Dist: tqdm
Requires-Dist: requests
Requires-Dist: shapely
Requires-Dist: mss
